ovos_hivemind_pipeline/__init__.py
ovos_hivemind_pipeline/version.py
ovos_hivemind_pipeline/locale/en-us/asking.dialog
ovos_hivemind_pipeline/locale/en-us/hivemind_error.dialog
ovos_hivemind_pipeline/locale/fr-fr/asking.dialog
ovos_hivemind_pipeline/locale/fr-fr/hivemind_error.dialog
ovos_hivemind_pipeline/locale/nl-nl/asking.dialog
ovos_hivemind_pipeline/locale/nl-nl/hivemind_error.dialog
ovos_hivemind_pipeline/locale/pt-pt/asking.dialog
ovos_hivemind_pipeline/locale/pt-pt/hivemind_error.dialog
ovos_hivemind_pipeline_plugin-0.0.3.dist-info/LICENSE
ovos_hivemind_pipeline_plugin-0.0.3.dist-info/METADATA
ovos_hivemind_pipeline_plugin-0.0.3.dist-info/WHEEL
ovos_hivemind_pipeline_plugin-0.0.3.dist-info/entry_points.txt
ovos_hivemind_pipeline_plugin-0.0.3.dist-info/top_level.txt
ovos_hivemind_pipeline_plugin-0.0.3.dist-info/RECORD
