Metadata-Version: 2.1
Name: ovos-hivemind-pipeline-plugin
Version: 0.0.3
Summary: hivemind pipeline plugin for OVOS
Home-page: https://github.com/JarbasHiveMind/ovos-hivemind-pipeline-plugin
Author: JarbasAI
License: Apache License 2.0
Keywords: natural language processing
Classifier: Development Status :: 5 - Production/Stable
Classifier: Intended Audience :: Developers
Classifier: Topic :: Text Processing :: Linguistic
Classifier: License :: OSI Approved :: Apache Software License
Classifier: Programming Language :: Python :: 3.10
Classifier: Programming Language :: Python :: 3.11
License-File: LICENSE
Requires-Dist: ovos-utils>=0.0.28
Requires-Dist: ovos-workshop>=0.0.11
Requires-Dist: ovos-plugin-manager>=0.0.26
Requires-Dist: ovos-translate-server-plugin
Requires-Dist: hivemind-bus-client>=0.0.4a22
